{
    "gameId": 3004935089,
    "platformId": "NA1",
    "gameCreation": 1553475323496,
    "gameDuration": 1715,
    "queueId": 0,
    "mapId": 11,
    "seasonId": 13,
    "gameVersion": "9.6.267.4221",
    "gameMode": "CLASSIC",
    "gameType": "CUSTOM_GAME",
    "teams": [
        {
            "teamId": 100,
            "win": "Win",
            "firstBlood": true,
            "firstTower": true,
            "firstInhibitor": true,
            "firstBaron": true,
            "firstDragon": true,
            "firstRiftHerald": true,
            "towerKills": 11,
            "inhibitorKills": 2,
            "baronKills": 1,
            "dragonKills": 3,
            "vilemawKills": 0,
            "riftHeraldKills": 1,
            "dominionVictoryScore": 0,
            "bans": [
                {
                    "championId": 143,
                    "pickTurn": 3
                },
                {
                    "championId": 122,
                    "pickTurn": 5
                },
                {
                    "championId": 15,
                    "pickTurn": 2
                },
                {
                    "championId": 51,
                    "pickTurn": 4
                }
            ]
        },
        {
            "teamId": 200,
            "win": "Fail",
            "firstBlood": false,
            "firstTower": false,
            "firstInhibitor": false,
            "firstBaron": false,
            "firstDragon": false,
            "firstRiftHerald": false,
            "towerKills": 0,
            "inhibitorKills": 0,
            "baronKills": 0,
            "dragonKills": 0,
            "vilemawKills": 0,
            "riftHeraldKills": 0,
            "dominionVictoryScore": 0,
            "bans": [
                {
                    "championId": 119,
                    "pickTurn": 2
                },
                {
                    "championId": 75,
                    "pickTurn": 4
                },
                {
                    "championId": 20,
                    "pickTurn": 6
                },
                {
                    "championId": 164,
                    "pickTurn": 1
                },
                {
                    "championId": 6,
                    "pickTurn": 3
                }
            ]
        }
    ],
    "participants": [
        {
            "participantId": 1,
            "teamId": 100,
            "championId": 96,
            "spell1Id": 1,
            "spell2Id": 4,
            "highestAchievedSeasonTier": "SILVER",
            "stats": {
                "participantId": 1,
                "win": true,
                "item0": 3285,
                "item1": 0,
                "item2": 3040,
                "item3": 3020,
                "item4": 1026,
                "item5": 1056,
                "item6": 3363,
                "kills": 8,
                "deaths": 2,
                "assists": 5,
                "largestKillingSpree": 4,
                "largestMultiKill": 1,
                "killingSprees": 2,
                "longestTimeSpentLiving": 786,
                "doubleKills": 0,
                "tripleKills": 0,
                "quadraKills": 0,
                "pentaKills": 0,
                "unrealKills": 0,
                "totalDamageDealt": 142199,
                "magicDamageDealt": 112533,
                "physicalDamageDealt": 20900,
                "trueDamageDealt": 8765,
                "largestCriticalStrike": 0,
                "totalDamageDealtToChampions": 18801,
                "magicDamageDealtToChampions": 16540,
                "physicalDamageDealtToChampions": 1400,
                "trueDamageDealtToChampions": 860,
                "totalHeal": 1548,
                "totalUnitsHealed": 1,
                "damageSelfMitigated": 3205,
                "damageDealtToObjectives": 9544,
                "damageDealtToTurrets": 4213,
                "visionScore": 9,
                "timeCCingOthers": 8,
                "totalDamageTaken": 7680,
                "magicalDamageTaken": 4038,
                "physicalDamageTaken": 2570,
                "trueDamageTaken": 1070,
                "goldEarned": 11604,
                "goldSpent": 8775,
                "turretKills": 2,
                "inhibitorKills": 2,
                "totalMinionsKilled": 193,
                "neutralMinionsKilled": 0,
                "neutralMinionsKilledTeamJungle": 0,
                "neutralMinionsKilledEnemyJungle": 0,
                "totalTimeCrowdControlDealt": 293,
                "champLevel": 15,
                "visionWardsBoughtInGame": 3,
                "sightWardsBoughtInGame": 0,
                "wardsPlaced": 7,
                "wardsKilled": 0,
                "firstBloodKill": false,
                "firstBloodAssist": false,
                "firstTowerKill": false,
                "firstTowerAssist": false,
                "firstInhibitorKill": true,
                "firstInhibitorAssist": false,
                "combatPlayerScore": 0,
                "objectivePlayerScore": 0,
                "totalPlayerScore": 0,
                "totalScoreRank": 0,
                "playerScore0": 0,
                "playerScore1": 0,
                "playerScore2": 0,
                "playerScore3": 0,
                "playerScore4": 0,
                "playerScore5": 0,
                "playerScore6": 0,
                "playerScore7": 0,
                "playerScore8": 0,
                "playerScore9": 0,
                "perk0": 8229,
                "perk0Var1": 1808,
                "perk0Var2": 0,
                "perk0Var3": 0,
                "perk1": 8226,
                "perk1Var1": 250,
                "perk1Var2": 1021,
                "perk1Var3": 0,
                "perk2": 8210,
                "perk2Var1": 0,
                "perk2Var2": 0,
                "perk2Var3": 0,
                "perk3": 8236,
                "perk3Var1": 24,
                "perk3Var2": 0,
                "perk3Var3": 0,
                "perk4": 8316,
                "perk4Var1": 2508,
                "perk4Var2": 0,
                "perk4Var3": 0,
                "perk5": 8304,
                "perk5Var1": 9,
                "perk5Var2": 0,
                "perk5Var3": 0,
                "perkPrimaryStyle": 8200,
                "perkSubStyle": 8300,
                "statPerk0": 5008,
                "statPerk1": 5008,
                "statPerk2": 5003
            },
            "timeline": {
                "participantId": 1,
                "creepsPerMinDeltas": {
                    "10-20": 6.8,
                    "0-10": 7
                },
                "xpPerMinDeltas": {
                    "10-20": 481.29999999999995,
                    "0-10": 459.9
                },
                "goldPerMinDeltas": {
                    "10-20": 387.5,
                    "0-10": 279.9
                },
                "csDiffPerMinDeltas": {
                    "10-20": 0.8999999999999999,
                    "0-10": 0.9000000000000004
                },
                "xpDiffPerMinDeltas": {
                    "10-20": 8.299999999999983,
                    "0-10": -37.49999999999997
                },
                "damageTakenPerMinDeltas": {
                    "10-20": 326.29999999999995,
                    "0-10": 179.7
                },
                "damageTakenDiffPerMinDeltas": {
                    "10-20": -317.5,
                    "0-10": -43.3
                },
                "role": "SOLO",
                "lane": "MIDDLE"
            }
        },
        {
            "participantId": 2,
            "teamId": 100,
            "championId": 80,
            "spell1Id": 14,
            "spell2Id": 4,
            "stats": {
                "participantId": 2,
                "win": true,
                "item0": 3142,
                "item1": 2033,
                "item2": 3111,
                "item3": 3147,
                "item4": 1037,
                "item5": 3133,
                "item6": 3364,
                "kills": 13,
                "deaths": 1,
                "assists": 5,
                "largestKillingSpree": 9,
                "largestMultiKill": 2,
                "killingSprees": 2,
                "longestTimeSpentLiving": 1109,
                "doubleKills": 2,
                "tripleKills": 0,
                "quadraKills": 0,
                "pentaKills": 0,
                "unrealKills": 0,
                "totalDamageDealt": 122778,
                "magicDamageDealt": 3087,
                "physicalDamageDealt": 113084,
                "trueDamageDealt": 6605,
                "largestCriticalStrike": 1089,
                "totalDamageDealtToChampions": 17835,
                "magicDamageDealtToChampions": 2087,
                "physicalDamageDealtToChampions": 15394,
                "trueDamageDealtToChampions": 354,
                "totalHeal": 2957,
                "totalUnitsHealed": 1,
                "damageSelfMitigated": 5121,
                "damageDealtToObjectives": 20840,
                "damageDealtToTurrets": 6162,
                "visionScore": 17,
                "timeCCingOthers": 20,
                "totalDamageTaken": 10533,
                "magicalDamageTaken": 4183,
                "physicalDamageTaken": 5842,
                "trueDamageTaken": 507,
                "goldEarned": 11565,
                "goldSpent": 9450,
                "turretKills": 2,
                "inhibitorKills": 0,
                "totalMinionsKilled": 138,
                "neutralMinionsKilled": 8,
                "neutralMinionsKilledTeamJungle": 0,
                "neutralMinionsKilledEnemyJungle": 0,
                "totalTimeCrowdControlDealt": 48,
                "champLevel": 13,
                "visionWardsBoughtInGame": 1,
                "sightWardsBoughtInGame": 0,
                "wardsPlaced": 3,
                "wardsKilled": 6,
                "firstBloodKill": false,
                "firstBloodAssist": false,
                "firstTowerKill": false,
                "firstTowerAssist": true,
                "firstInhibitorKill": false,
                "firstInhibitorAssist": true,
                "combatPlayerScore": 0,
                "objectivePlayerScore": 0,
                "totalPlayerScore": 0,
                "totalScoreRank": 0,
                "playerScore0": 0,
                "playerScore1": 0,
                "playerScore2": 0,
                "playerScore3": 0,
                "playerScore4": 0,
                "playerScore5": 0,
                "playerScore6": 0,
                "playerScore7": 0,
                "playerScore8": 0,
                "playerScore9": 0,
                "perk0": 8112,
                "perk0Var1": 1083,
                "perk0Var2": 0,
                "perk0Var3": 0,
                "perk1": 8143,
                "perk1Var1": 433,
                "perk1Var2": 0,
                "perk1Var3": 0,
                "perk2": 8138,
                "perk2Var1": 18,
                "perk2Var2": 0,
                "perk2Var3": 0,
                "perk3": 8135,
                "perk3Var1": 2394,
                "perk3Var2": 5,
                "perk3Var3": 0,
                "perk4": 8237,
                "perk4Var1": 311,
                "perk4Var2": 0,
                "perk4Var3": 0,
                "perk5": 8233,
                "perk5Var1": 22,
                "perk5Var2": 0,
                "perk5Var3": 0,
                "perkPrimaryStyle": 8100,
                "perkSubStyle": 8200,
                "statPerk0": 5008,
                "statPerk1": 5008,
                "statPerk2": 5001
            },
            "timeline": {
                "participantId": 2,
                "creepsPerMinDeltas": {
                    "10-20": 5.199999999999999,
                    "0-10": 5.1
                },
                "xpPerMinDeltas": {
                    "10-20": 369.2,
                    "0-10": 322.70000000000005
                },
                "goldPerMinDeltas": {
                    "10-20": 381.5,
                    "0-10": 326.9
                },
                "csDiffPerMinDeltas": {
                    "10-20": -0.7000000000000002,
                    "0-10": 0
                },
                "xpDiffPerMinDeltas": {
                    "10-20": -59.80000000000004,
                    "0-10": 123.49999999999999
                },
                "damageTakenPerMinDeltas": {
                    "10-20": 472.6,
                    "0-10": 273.5
                },
                "damageTakenDiffPerMinDeltas": {
                    "10-20": 134.10000000000002,
                    "0-10": -103.4
                },
                "role": "DUO_CARRY",
                "lane": "BOTTOM"
            }
        },
        {
            "participantId": 3,
            "teamId": 100,
            "championId": 33,
            "spell1Id": 11,
            "spell2Id": 4,
            "highestAchievedSeasonTier": "SILVER",
            "stats": {
                "participantId": 3,
                "win": true,
                "item0": 3065,
                "item1": 1401,
                "item2": 1031,
                "item3": 3111,
                "item4": 1011,
                "item5": 0,
                "item6": 3364,
                "kills": 4,
                "deaths": 2,
                "assists": 12,
                "largestKillingSpree": 4,
                "largestMultiKill": 1,
                "killingSprees": 1,
                "longestTimeSpentLiving": 1133,
                "doubleKills": 0,
                "tripleKills": 0,
                "quadraKills": 0,
                "pentaKills": 0,
                "unrealKills": 0,
                "totalDamageDealt": 95714,
                "magicDamageDealt": 54527,
                "physicalDamageDealt": 28215,
                "trueDamageDealt": 12971,
                "largestCriticalStrike": 0,
                "totalDamageDealtToChampions": 6284,
                "magicDamageDealtToChampions": 3997,
                "physicalDamageDealtToChampions": 1673,
                "trueDamageDealtToChampions": 614,
                "totalHeal": 9619,
                "totalUnitsHealed": 1,
                "damageSelfMitigated": 26141,
                "damageDealtToObjectives": 23923,
                "damageDealtToTurrets": 3980,
                "visionScore": 35,
                "timeCCingOthers": 26,
                "totalDamageTaken": 23988,
                "magicalDamageTaken": 4307,
                "physicalDamageTaken": 18169,
                "trueDamageTaken": 1511,
                "goldEarned": 10199,
                "goldSpent": 8800,
                "turretKills": 3,
                "inhibitorKills": 0,
                "totalMinionsKilled": 15,
                "neutralMinionsKilled": 90,
                "neutralMinionsKilledTeamJungle": 54,
                "neutralMinionsKilledEnemyJungle": 0,
                "totalTimeCrowdControlDealt": 436,
                "champLevel": 13,
                "visionWardsBoughtInGame": 6,
                "sightWardsBoughtInGame": 0,
                "wardsPlaced": 12,
                "wardsKilled": 4,
                "firstBloodKill": false,
                "firstBloodAssist": false,
                "firstTowerKill": false,
                "firstTowerAssist": false,
                "firstInhibitorKill": false,
                "firstInhibitorAssist": false,
                "combatPlayerScore": 0,
                "objectivePlayerScore": 0,
                "totalPlayerScore": 0,
                "totalScoreRank": 0,
                "playerScore0": 0,
                "playerScore1": 0,
                "playerScore2": 0,
                "playerScore3": 0,
                "playerScore4": 0,
                "playerScore5": 0,
                "playerScore6": 0,
                "playerScore7": 0,
                "playerScore8": 0,
                "playerScore9": 0,
                "perk0": 8439,
                "perk0Var1": 503,
                "perk0Var2": 0,
                "perk0Var3": 0,
                "perk1": 8446,
                "perk1Var1": 1064,
                "perk1Var2": 0,
                "perk1Var3": 0,
                "perk2": 8429,
                "perk2Var1": 65,
                "perk2Var2": 15,
                "perk2Var3": 14,
                "perk3": 8242,
                "perk3Var1": 19,
                "perk3Var2": 0,
                "perk3Var3": 0,
                "perk4": 9111,
                "perk4Var1": 836,
                "perk4Var2": 320,
                "perk4Var3": 0,
                "perk5": 8014,
                "perk5Var1": 182,
                "perk5Var2": 0,
                "perk5Var3": 0,
                "perkPrimaryStyle": 8400,
                "perkSubStyle": 8000,
                "statPerk0": 5005,
                "statPerk1": 5008,
                "statPerk2": 5002
            },
            "timeline": {
                "participantId": 3,
                "creepsPerMinDeltas": {
                    "10-20": 0.2,
                    "0-10": 0.1
                },
                "xpPerMinDeltas": {
                    "10-20": 346.70000000000005,
                    "0-10": 294.6
                },
                "goldPerMinDeltas": {
                    "10-20": 330,
                    "0-10": 312.5
                },
                "csDiffPerMinDeltas": {
                    "10-20": -0.2,
                    "0-10": 0
                },
                "xpDiffPerMinDeltas": {
                    "10-20": -75.49999999999997,
                    "0-10": 33.00000000000003
                },
                "damageTakenPerMinDeltas": {
                    "10-20": 834.2,
                    "0-10": 535.2
                },
                "damageTakenDiffPerMinDeltas": {
                    "10-20": -72.90000000000003,
                    "0-10": -119.20000000000002
                },
                "role": "NONE",
                "lane": "JUNGLE"
            }
        },
        {
            "participantId": 4,
            "teamId": 100,
            "championId": 412,
            "spell1Id": 7,
            "spell2Id": 4,
            "highestAchievedSeasonTier": "PLATINUM",
            "stats": {
                "participantId": 4,
                "win": true,
                "item0": 3117,
                "item1": 0,
                "item2": 3050,
                "item3": 1031,
                "item4": 1028,
                "item5": 3069,
                "item6": 3364,
                "kills": 0,
                "deaths": 4,
                "assists": 17,
                "largestKillingSpree": 0,
                "largestMultiKill": 0,
                "killingSprees": 0,
                "longestTimeSpentLiving": 859,
                "doubleKills": 0,
                "tripleKills": 0,
                "quadraKills": 0,
                "pentaKills": 0,
                "unrealKills": 0,
                "totalDamageDealt": 17041,
                "magicDamageDealt": 11418,
                "physicalDamageDealt": 5298,
                "trueDamageDealt": 324,
                "largestCriticalStrike": 0,
                "totalDamageDealtToChampions": 6523,
                "magicDamageDealtToChampions": 5308,
                "physicalDamageDealtToChampions": 1214,
                "trueDamageDealtToChampions": 0,
                "totalHeal": 2976,
                "totalUnitsHealed": 5,
                "damageSelfMitigated": 11383,
                "damageDealtToObjectives": 2498,
                "damageDealtToTurrets": 1124,
                "visionScore": 64,
                "timeCCingOthers": 32,
                "totalDamageTaken": 14902,
                "magicalDamageTaken": 6132,
                "physicalDamageTaken": 6895,
                "trueDamageTaken": 1874,
                "goldEarned": 7883,
                "goldSpent": 6225,
                "turretKills": 0,
                "inhibitorKills": 0,
                "totalMinionsKilled": 18,
                "neutralMinionsKilled": 0,
                "neutralMinionsKilledTeamJungle": 0,
                "neutralMinionsKilledEnemyJungle": 0,
                "totalTimeCrowdControlDealt": 94,
                "champLevel": 12,
                "visionWardsBoughtInGame": 3,
                "sightWardsBoughtInGame": 0,
                "wardsPlaced": 31,
                "wardsKilled": 5,
                "firstBloodKill": false,
                "firstBloodAssist": false,
                "firstTowerKill": false,
                "firstTowerAssist": false,
                "firstInhibitorKill": false,
                "firstInhibitorAssist": false,
                "combatPlayerScore": 0,
                "objectivePlayerScore": 0,
                "totalPlayerScore": 0,
                "totalScoreRank": 0,
                "playerScore0": 0,
                "playerScore1": 0,
                "playerScore2": 0,
                "playerScore3": 0,
                "playerScore4": 0,
                "playerScore5": 0,
                "playerScore6": 0,
                "playerScore7": 0,
                "playerScore8": 0,
                "playerScore9": 0,
                "perk0": 8439,
                "perk0Var1": 488,
                "perk0Var2": 0,
                "perk0Var3": 0,
                "perk1": 8463,
                "perk1Var1": 843,
                "perk1Var2": 0,
                "perk1Var3": 0,
                "perk2": 8473,
                "perk2Var1": 226,
                "perk2Var2": 0,
                "perk2Var3": 0,
                "perk3": 8451,
                "perk3Var1": 122,
                "perk3Var2": 0,
                "perk3Var3": 0,
                "perk4": 8347,
                "perk4Var1": 0,
                "perk4Var2": 0,
                "perk4Var3": 0,
                "perk5": 8345,
                "perk5Var1": 4,
                "perk5Var2": 0,
                "perk5Var3": 0,
                "perkPrimaryStyle": 8400,
                "perkSubStyle": 8300,
                "statPerk0": 5007,
                "statPerk1": 5002,
                "statPerk2": 5002
            },
            "timeline": {
                "participantId": 4,
                "creepsPerMinDeltas": {
                    "10-20": 0.2,
                    "0-10": 0.7
                },
                "xpPerMinDeltas": {
                    "10-20": 312.6,
                    "0-10": 310.4
                },
                "goldPerMinDeltas": {
                    "10-20": 238.8,
                    "0-10": 230.9
                },
                "csDiffPerMinDeltas": {
                    "10-20": -0.7000000000000002,
                    "0-10": 0
                },
                "xpDiffPerMinDeltas": {
                    "10-20": -59.80000000000004,
                    "0-10": 123.49999999999999
                },
                "damageTakenPerMinDeltas": {
                    "10-20": 724,
                    "0-10": 267
                },
                "damageTakenDiffPerMinDeltas": {
                    "10-20": 134.10000000000002,
                    "0-10": -103.4
                },
                "role": "DUO_SUPPORT",
                "lane": "BOTTOM"
            }
        },
        {
            "participantId": 5,
            "teamId": 100,
            "championId": 78,
            "spell1Id": 12,
            "spell2Id": 4,
            "highestAchievedSeasonTier": "GOLD",
            "stats": {
                "participantId": 5,
                "win": true,
                "item0": 3065,
                "item1": 2055,
                "item2": 3105,
                "item3": 3025,
                "item4": 3111,
                "item5": 0,
                "item6": 3364,
                "kills": 3,
                "deaths": 2,
                "assists": 8,
                "largestKillingSpree": 2,
                "largestMultiKill": 1,
                "killingSprees": 1,
                "longestTimeSpentLiving": 1108,
                "doubleKills": 0,
                "tripleKills": 0,
                "quadraKills": 0,
                "pentaKills": 0,
                "unrealKills": 0,
                "totalDamageDealt": 83850,
                "magicDamageDealt": 3916,
                "physicalDamageDealt": 72653,
                "trueDamageDealt": 7279,
                "largestCriticalStrike": 0,
                "totalDamageDealtToChampions": 9106,
                "magicDamageDealtToChampions": 1282,
                "physicalDamageDealtToChampions": 7673,
                "trueDamageDealtToChampions": 150,
                "totalHeal": 1519,
                "totalUnitsHealed": 1,
                "damageSelfMitigated": 16714,
                "damageDealtToObjectives": 9564,
                "damageDealtToTurrets": 4807,
                "visionScore": 13,
                "timeCCingOthers": 27,
                "totalDamageTaken": 12440,
                "magicalDamageTaken": 5432,
                "physicalDamageTaken": 5884,
                "trueDamageTaken": 1123,
                "goldEarned": 10271,
                "goldSpent": 8350,
                "turretKills": 0,
                "inhibitorKills": 0,
                "totalMinionsKilled": 153,
                "neutralMinionsKilled": 6,
                "neutralMinionsKilledTeamJungle": 0,
                "neutralMinionsKilledEnemyJungle": 6,
                "totalTimeCrowdControlDealt": 459,
                "champLevel": 14,
                "visionWardsBoughtInGame": 2,
                "sightWardsBoughtInGame": 0,
                "wardsPlaced": 5,
                "wardsKilled": 2,
                "firstBloodKill": true,
                "firstBloodAssist": false,
                "firstTowerKill": false,
                "firstTowerAssist": false,
                "firstInhibitorKill": false,
                "firstInhibitorAssist": true,
                "combatPlayerScore": 0,
                "objectivePlayerScore": 0,
                "totalPlayerScore": 0,
                "totalScoreRank": 0,
                "playerScore0": 0,
                "playerScore1": 0,
                "playerScore2": 0,
                "playerScore3": 0,
                "playerScore4": 0,
                "playerScore5": 0,
                "playerScore6": 0,
                "playerScore7": 0,
                "playerScore8": 0,
                "playerScore9": 0,
                "perk0": 8439,
                "perk0Var1": 357,
                "perk0Var2": 0,
                "perk0Var3": 0,
                "perk1": 8401,
                "perk1Var1": 80,
                "perk1Var2": 0,
                "perk1Var3": 0,
                "perk2": 8473,
                "perk2Var1": 411,
                "perk2Var2": 0,
                "perk2Var3": 0,
                "perk3": 8453,
                "perk3Var1": 188,
                "perk3Var2": 761,
                "perk3Var3": 0,
                "perk4": 9111,
                "perk4Var1": 407,
                "perk4Var2": 220,
                "perk4Var3": 0,
                "perk5": 9105,
                "perk5Var1": 15,
                "perk5Var2": 30,
                "perk5Var3": 0,
                "perkPrimaryStyle": 8400,
                "perkSubStyle": 8000,
                "statPerk0": 5005,
                "statPerk1": 5002,
                "statPerk2": 5003
            },
            "timeline": {
                "participantId": 5,
                "creepsPerMinDeltas": {
                    "10-20": 6.8,
                    "0-10": 5.6
                },
                "xpPerMinDeltas": {
                    "10-20": 454.2,
                    "0-10": 449.29999999999995
                },
                "goldPerMinDeltas": {
                    "10-20": 339.9,
                    "0-10": 306
                },
                "csDiffPerMinDeltas": {
                    "10-20": 1.9,
                    "0-10": 0.09999999999999964
                },
                "xpDiffPerMinDeltas": {
                    "10-20": 85.89999999999998,
                    "0-10": 70.69999999999999
                },
                "damageTakenPerMinDeltas": {
                    "10-20": 683.4,
                    "0-10": 192
                },
                "damageTakenDiffPerMinDeltas": {
                    "10-20": -91.70000000000005,
                    "0-10": -147.79999999999998
                },
                "role": "SOLO",
                "lane": "TOP"
            }
        },
        {
            "participantId": 6,
            "teamId": 200,
            "championId": 103,
            "spell1Id": 14,
            "spell2Id": 4,
            "highestAchievedSeasonTier": "GOLD",
            "stats": {
                "participantId": 6,
                "win": false,
                "item0": 3285,
                "item1": 3157,
                "item2": 3020,
                "item3": 3145,
                "item4": 1056,
                "item5": 1028,
                "item6": 3340,
                "kills": 5,
                "deaths": 3,
                "assists": 4,
                "largestKillingSpree": 4,
                "largestMultiKill": 1,
                "killingSprees": 1,
                "longestTimeSpentLiving": 1123,
                "doubleKills": 0,
                "tripleKills": 0,
                "quadraKills": 0,
                "pentaKills": 0,
                "unrealKills": 0,
                "totalDamageDealt": 108758,
                "magicDamageDealt": 62400,
                "physicalDamageDealt": 13095,
                "trueDamageDealt": 33262,
                "largestCriticalStrike": 0,
                "totalDamageDealtToChampions": 13590,
                "magicDamageDealtToChampions": 8642,
                "physicalDamageDealtToChampions": 596,
                "trueDamageDealtToChampions": 4351,
                "totalHeal": 2075,
                "totalUnitsHealed": 1,
                "damageSelfMitigated": 5231,
                "damageDealtToObjectives": 961,
                "damageDealtToTurrets": 217,
                "visionScore": 10,
                "timeCCingOthers": 11,
                "totalDamageTaken": 13766,
                "magicalDamageTaken": 8702,
                "physicalDamageTaken": 4417,
                "trueDamageTaken": 646,
                "goldEarned": 9365,
                "goldSpent": 8950,
                "turretKills": 0,
                "inhibitorKills": 0,
                "totalMinionsKilled": 173,
                "neutralMinionsKilled": 0,
                "neutralMinionsKilledTeamJungle": 0,
                "neutralMinionsKilledEnemyJungle": 0,
                "totalTimeCrowdControlDealt": 62,
                "champLevel": 14,
                "visionWardsBoughtInGame": 0,
                "sightWardsBoughtInGame": 0,
                "wardsPlaced": 9,
                "wardsKilled": 0,
                "firstBloodKill": false,
                "firstBloodAssist": false,
                "firstTowerKill": false,
                "firstTowerAssist": false,
                "firstInhibitorKill": false,
                "firstInhibitorAssist": false,
                "combatPlayerScore": 0,
                "objectivePlayerScore": 0,
                "totalPlayerScore": 0,
                "totalScoreRank": 0,
                "playerScore0": 0,
                "playerScore1": 0,
                "playerScore2": 0,
                "playerScore3": 0,
                "playerScore4": 0,
                "playerScore5": 0,
                "playerScore6": 0,
                "playerScore7": 0,
                "playerScore8": 0,
                "playerScore9": 0,
                "perk0": 8214,
                "perk0Var1": 862,
                "perk0Var2": 0,
                "perk0Var3": 0,
                "perk1": 8226,
                "perk1Var1": 250,
                "perk1Var2": 525,
                "perk1Var3": 0,
                "perk2": 8233,
                "perk2Var1": 18,
                "perk2Var2": 50,
                "perk2Var3": 0,
                "perk3": 8236,
                "perk3Var1": 24,
                "perk3Var2": 0,
                "perk3Var3": 0,
                "perk4": 8313,
                "perk4Var1": 0,
                "perk4Var2": 0,
                "perk4Var3": 0,
                "perk5": 8345,
                "perk5Var1": 4,
                "perk5Var2": 0,
                "perk5Var3": 0,
                "perkPrimaryStyle": 8200,
                "perkSubStyle": 8300,
                "statPerk0": 5008,
                "statPerk1": 5008,
                "statPerk2": 5001
            },
            "timeline": {
                "participantId": 6,
                "creepsPerMinDeltas": {
                    "10-20": 5.9,
                    "0-10": 6.1
                },
                "xpPerMinDeltas": {
                    "10-20": 473,
                    "0-10": 497.4
                },
                "goldPerMinDeltas": {
                    "10-20": 365.79999999999995,
                    "0-10": 257.5
                },
                "csDiffPerMinDeltas": {
                    "10-20": -0.8999999999999999,
                    "0-10": -0.9000000000000004
                },
                "xpDiffPerMinDeltas": {
                    "10-20": -8.299999999999983,
                    "0-10": 37.49999999999997
                },
                "damageTakenPerMinDeltas": {
                    "10-20": 643.8,
                    "0-10": 223
                },
                "damageTakenDiffPerMinDeltas": {
                    "10-20": 317.5,
                    "0-10": 43.3
                },
                "role": "SOLO",
                "lane": "MIDDLE"
            }
        },
        {
            "participantId": 7,
            "teamId": 200,
            "championId": 84,
            "spell1Id": 4,
            "spell2Id": 14,
            "stats": {
                "participantId": 7,
                "win": false,
                "item0": 3146,
                "item1": 3057,
                "item2": 3020,
                "item3": 1054,
                "item4": 3113,
                "item5": 1026,
                "item6": 3340,
                "kills": 1,
                "deaths": 7,
                "assists": 3,
                "largestKillingSpree": 0,
                "largestMultiKill": 1,
                "killingSprees": 0,
                "longestTimeSpentLiving": 553,
                "doubleKills": 0,
                "tripleKills": 0,
                "quadraKills": 0,
                "pentaKills": 0,
                "unrealKills": 0,
                "totalDamageDealt": 64597,
                "magicDamageDealt": 43779,
                "physicalDamageDealt": 20000,
                "trueDamageDealt": 818,
                "largestCriticalStrike": 0,
                "totalDamageDealtToChampions": 8529,
                "magicDamageDealtToChampions": 5556,
                "physicalDamageDealtToChampions": 2155,
                "trueDamageDealtToChampions": 818,
                "totalHeal": 4457,
                "totalUnitsHealed": 1,
                "damageSelfMitigated": 7484,
                "damageDealtToObjectives": 0,
                "damageDealtToTurrets": 0,
                "visionScore": 11,
                "timeCCingOthers": 3,
                "totalDamageTaken": 19248,
                "magicalDamageTaken": 5900,
                "physicalDamageTaken": 12664,
                "trueDamageTaken": 684,
                "goldEarned": 8099,
                "goldSpent": 7750,
                "turretKills": 0,
                "inhibitorKills": 0,
                "totalMinionsKilled": 130,
                "neutralMinionsKilled": 12,
                "neutralMinionsKilledTeamJungle": 12,
                "neutralMinionsKilledEnemyJungle": 0,
                "totalTimeCrowdControlDealt": 33,
                "champLevel": 12,
                "visionWardsBoughtInGame": 0,
                "sightWardsBoughtInGame": 0,
                "wardsPlaced": 6,
                "wardsKilled": 2,
                "firstBloodKill": false,
                "firstBloodAssist": false,
                "firstTowerKill": false,
                "firstTowerAssist": false,
                "firstInhibitorKill": false,
                "firstInhibitorAssist": false,
                "combatPlayerScore": 0,
                "objectivePlayerScore": 0,
                "totalPlayerScore": 0,
                "totalScoreRank": 0,
                "playerScore0": 0,
                "playerScore1": 0,
                "playerScore2": 0,
                "playerScore3": 0,
                "playerScore4": 0,
                "playerScore5": 0,
                "playerScore6": 0,
                "playerScore7": 0,
                "playerScore8": 0,
                "playerScore9": 0,
                "perk0": 8112,
                "perk0Var1": 543,
                "perk0Var2": 0,
                "perk0Var3": 0,
                "perk1": 8139,
                "perk1Var1": 567,
                "perk1Var2": 0,
                "perk1Var3": 0,
                "perk2": 8138,
                "perk2Var1": 7,
                "perk2Var2": 0,
                "perk2Var3": 0,
                "perk3": 8135,
                "perk3Var1": 692,
                "perk3Var2": 4,
                "perk3Var3": 0,
                "perk4": 8304,
                "perk4Var1": 10,
                "perk4Var2": 0,
                "perk4Var3": 0,
                "perk5": 8352,
                "perk5Var1": 101,
                "perk5Var2": 525,
                "perk5Var3": 0,
                "perkPrimaryStyle": 8100,
                "perkSubStyle": 8300,
                "statPerk0": 5008,
                "statPerk1": 5008,
                "statPerk2": 5001
            },
            "timeline": {
                "participantId": 7,
                "creepsPerMinDeltas": {
                    "10-20": 4.9,
                    "0-10": 5.5
                },
                "xpPerMinDeltas": {
                    "10-20": 368.3,
                    "0-10": 378.6
                },
                "goldPerMinDeltas": {
                    "10-20": 335.6,
                    "0-10": 213.2
                },
                "csDiffPerMinDeltas": {
                    "10-20": -1.9,
                    "0-10": -0.09999999999999964
                },
                "xpDiffPerMinDeltas": {
                    "10-20": -85.89999999999998,
                    "0-10": -70.69999999999999
                },
                "damageTakenPerMinDeltas": {
                    "10-20": 775.1,
                    "0-10": 339.79999999999995
                },
                "damageTakenDiffPerMinDeltas": {
                    "10-20": 91.70000000000005,
                    "0-10": 147.79999999999998
                },
                "role": "SOLO",
                "lane": "TOP"
            }
        },
        {
            "participantId": 8,
            "teamId": 200,
            "championId": 254,
            "spell1Id": 4,
            "spell2Id": 11,
            "stats": {
                "participantId": 8,
                "win": false,
                "item0": 2055,
                "item1": 2032,
                "item2": 3078,
                "item3": 3047,
                "item4": 1400,
                "item5": 0,
                "item6": 3364,
                "kills": 2,
                "deaths": 9,
                "assists": 2,
                "largestKillingSpree": 0,
                "largestMultiKill": 1,
                "killingSprees": 0,
                "longestTimeSpentLiving": 387,
                "doubleKills": 0,
                "tripleKills": 0,
                "quadraKills": 0,
                "pentaKills": 0,
                "unrealKills": 0,
                "totalDamageDealt": 125011,
                "magicDamageDealt": 6355,
                "physicalDamageDealt": 100500,
                "trueDamageDealt": 18156,
                "largestCriticalStrike": 0,
                "totalDamageDealtToChampions": 4636,
                "magicDamageDealtToChampions": 73,
                "physicalDamageDealtToChampions": 3808,
                "trueDamageDealtToChampions": 754,
                "totalHeal": 5434,
                "totalUnitsHealed": 1,
                "damageSelfMitigated": 16506,
                "damageDealtToObjectives": 3588,
                "damageDealtToTurrets": 171,
                "visionScore": 17,
                "timeCCingOthers": 12,
                "totalDamageTaken": 21876,
                "magicalDamageTaken": 7664,
                "physicalDamageTaken": 13805,
                "trueDamageTaken": 406,
                "goldEarned": 8478,
                "goldSpent": 8083,
                "turretKills": 0,
                "inhibitorKills": 0,
                "totalMinionsKilled": 20,
                "neutralMinionsKilled": 113,
                "neutralMinionsKilledTeamJungle": 95,
                "neutralMinionsKilledEnemyJungle": 4,
                "totalTimeCrowdControlDealt": 227,
                "champLevel": 12,
                "visionWardsBoughtInGame": 3,
                "sightWardsBoughtInGame": 0,
                "wardsPlaced": 5,
                "wardsKilled": 3,
                "firstBloodKill": false,
                "firstBloodAssist": false,
                "firstTowerKill": false,
                "firstTowerAssist": false,
                "firstInhibitorKill": false,
                "firstInhibitorAssist": false,
                "combatPlayerScore": 0,
                "objectivePlayerScore": 0,
                "totalPlayerScore": 0,
                "totalScoreRank": 0,
                "playerScore0": 0,
                "playerScore1": 0,
                "playerScore2": 0,
                "playerScore3": 0,
                "playerScore4": 0,
                "playerScore5": 0,
                "playerScore6": 0,
                "playerScore7": 0,
                "playerScore8": 0,
                "playerScore9": 0,
                "perk0": 8112,
                "perk0Var1": 321,
                "perk0Var2": 0,
                "perk0Var3": 0,
                "perk1": 8143,
                "perk1Var1": 94,
                "perk1Var2": 0,
                "perk1Var3": 0,
                "perk2": 8120,
                "perk2Var1": 4,
                "perk2Var2": 5,
                "perk2Var3": 0,
                "perk3": 8105,
                "perk3Var1": 7,
                "perk3Var2": 2,
                "perk3Var3": 0,
                "perk4": 9111,
                "perk4Var1": 161,
                "perk4Var2": 80,
                "perk4Var3": 0,
                "perk5": 8014,
                "perk5Var1": 44,
                "perk5Var2": 0,
                "perk5Var3": 0,
                "perkPrimaryStyle": 8100,
                "perkSubStyle": 8000,
                "statPerk0": 5005,
                "statPerk1": 5008,
                "statPerk2": 5002
            },
            "timeline": {
                "participantId": 8,
                "creepsPerMinDeltas": {
                    "10-20": 0.4,
                    "0-10": 0.1
                },
                "xpPerMinDeltas": {
                    "10-20": 422.2,
                    "0-10": 261.6
                },
                "goldPerMinDeltas": {
                    "10-20": 343.2,
                    "0-10": 235.2
                },
                "csDiffPerMinDeltas": {
                    "10-20": 0.2,
                    "0-10": 0
                },
                "xpDiffPerMinDeltas": {
                    "10-20": 75.49999999999997,
                    "0-10": -33.00000000000003
                },
                "damageTakenPerMinDeltas": {
                    "10-20": 907.1,
                    "0-10": 654.4000000000001
                },
                "damageTakenDiffPerMinDeltas": {
                    "10-20": 72.90000000000003,
                    "0-10": 119.20000000000002
                },
                "role": "NONE",
                "lane": "JUNGLE"
            }
        },
        {
            "participantId": 9,
            "teamId": 200,
            "championId": 81,
            "spell1Id": 4,
            "spell2Id": 7,
            "highestAchievedSeasonTier": "PLATINUM",
            "stats": {
                "participantId": 9,
                "win": false,
                "item0": 2031,
                "item1": 3042,
                "item2": 3145,
                "item3": 3025,
                "item4": 3020,
                "item5": 1055,
                "item6": 3340,
                "kills": 3,
                "deaths": 1,
                "assists": 6,
                "largestKillingSpree": 3,
                "largestMultiKill": 1,
                "killingSprees": 1,
                "longestTimeSpentLiving": 597,
                "doubleKills": 0,
                "tripleKills": 0,
                "quadraKills": 0,
                "pentaKills": 0,
                "unrealKills": 0,
                "totalDamageDealt": 76471,
                "magicDamageDealt": 18259,
                "physicalDamageDealt": 58046,
                "trueDamageDealt": 165,
                "largestCriticalStrike": 0,
                "totalDamageDealtToChampions": 14725,
                "magicDamageDealtToChampions": 6535,
                "physicalDamageDealtToChampions": 8024,
                "trueDamageDealtToChampions": 165,
                "totalHeal": 1048,
                "totalUnitsHealed": 2,
                "damageSelfMitigated": 2699,
                "damageDealtToObjectives": 451,
                "damageDealtToTurrets": 190,
                "visionScore": 18,
                "timeCCingOthers": 7,
                "totalDamageTaken": 6683,
                "magicalDamageTaken": 3479,
                "physicalDamageTaken": 3034,
                "trueDamageTaken": 170,
                "goldEarned": 9328,
                "goldSpent": 7675,
                "turretKills": 0,
                "inhibitorKills": 0,
                "totalMinionsKilled": 137,
                "neutralMinionsKilled": 0,
                "neutralMinionsKilledTeamJungle": 0,
                "neutralMinionsKilledEnemyJungle": 0,
                "totalTimeCrowdControlDealt": 203,
                "champLevel": 13,
                "visionWardsBoughtInGame": 1,
                "sightWardsBoughtInGame": 0,
                "wardsPlaced": 12,
                "wardsKilled": 1,
                "firstBloodKill": false,
                "firstBloodAssist": false,
                "firstTowerKill": false,
                "firstTowerAssist": false,
                "firstInhibitorKill": false,
                "firstInhibitorAssist": false,
                "combatPlayerScore": 0,
                "objectivePlayerScore": 0,
                "totalPlayerScore": 0,
                "totalScoreRank": 0,
                "playerScore0": 0,
                "playerScore1": 0,
                "playerScore2": 0,
                "playerScore3": 0,
                "playerScore4": 0,
                "playerScore5": 0,
                "playerScore6": 0,
                "playerScore7": 0,
                "playerScore8": 0,
                "playerScore9": 0,
                "perk0": 8359,
                "perk0Var1": 805,
                "perk0Var2": 22,
                "perk0Var3": 0,
                "perk1": 8304,
                "perk1Var1": 10,
                "perk1Var2": 0,
                "perk1Var3": 0,
                "perk2": 8321,
                "perk2Var1": 0,
                "perk2Var2": 0,
                "perk2Var3": 0,
                "perk3": 8347,
                "perk3Var1": 0,
                "perk3Var2": 0,
                "perk3Var3": 0,
                "perk4": 8143,
                "perk4Var1": 221,
                "perk4Var2": 0,
                "perk4Var3": 0,
                "perk5": 8120,
                "perk5Var1": 0,
                "perk5Var2": 1,
                "perk5Var3": 0,
                "perkPrimaryStyle": 8300,
                "perkSubStyle": 8100,
                "statPerk0": 5008,
                "statPerk1": 5008,
                "statPerk2": 5002
            },
            "timeline": {
                "participantId": 9,
                "creepsPerMinDeltas": {
                    "10-20": 5.2,
                    "0-10": 5.1
                },
                "xpPerMinDeltas": {
                    "10-20": 475,
                    "0-10": 237.70000000000002
                },
                "goldPerMinDeltas": {
                    "10-20": 388.20000000000005,
                    "0-10": 255.4
                },
                "csDiffPerMinDeltas": {
                    "10-20": 0.7000000000000002,
                    "0-10": 0
                },
                "xpDiffPerMinDeltas": {
                    "10-20": 59.80000000000004,
                    "0-10": -123.49999999999999
                },
                "damageTakenPerMinDeltas": {
                    "10-20": 193,
                    "0-10": 261.2
                },
                "damageTakenDiffPerMinDeltas": {
                    "10-20": -134.10000000000002,
                    "0-10": 103.4
                },
                "role": "DUO_CARRY",
                "lane": "BOTTOM"
            }
        },
        {
            "participantId": 10,
            "teamId": 200,
            "championId": 89,
            "spell1Id": 4,
            "spell2Id": 3,
            "highestAchievedSeasonTier": "GOLD",
            "stats": {
                "participantId": 10,
                "win": false,
                "item0": 3105,
                "item1": 3401,
                "item2": 3047,
                "item3": 1033,
                "item4": 2055,
                "item5": 0,
                "item6": 3364,
                "kills": 0,
                "deaths": 8,
                "assists": 3,
                "largestKillingSpree": 0,
                "largestMultiKill": 0,
                "killingSprees": 0,
                "longestTimeSpentLiving": 677,
                "doubleKills": 0,
                "tripleKills": 0,
                "quadraKills": 0,
                "pentaKills": 0,
                "unrealKills": 0,
                "totalDamageDealt": 19770,
                "magicDamageDealt": 4061,
                "physicalDamageDealt": 5826,
                "trueDamageDealt": 9882,
                "largestCriticalStrike": 0,
                "totalDamageDealtToChampions": 2764,
                "magicDamageDealtToChampions": 2126,
                "physicalDamageDealtToChampions": 638,
                "trueDamageDealtToChampions": 0,
                "totalHeal": 701,
                "totalUnitsHealed": 5,
                "damageSelfMitigated": 17996,
                "damageDealtToObjectives": 499,
                "damageDealtToTurrets": 446,
                "visionScore": 36,
                "timeCCingOthers": 15,
                "totalDamageTaken": 16097,
                "magicalDamageTaken": 5110,
                "physicalDamageTaken": 10915,
                "trueDamageTaken": 72,
                "goldEarned": 5404,
                "goldSpent": 4700,
                "turretKills": 0,
                "inhibitorKills": 0,
                "totalMinionsKilled": 42,
                "neutralMinionsKilled": 0,
                "neutralMinionsKilledTeamJungle": 0,
                "neutralMinionsKilledEnemyJungle": 0,
                "totalTimeCrowdControlDealt": 32,
                "champLevel": 10,
                "visionWardsBoughtInGame": 6,
                "sightWardsBoughtInGame": 0,
                "wardsPlaced": 24,
                "wardsKilled": 4,
                "firstBloodKill": false,
                "firstBloodAssist": false,
                "firstTowerKill": false,
                "firstTowerAssist": false,
                "firstInhibitorKill": false,
                "firstInhibitorAssist": false,
                "combatPlayerScore": 0,
                "objectivePlayerScore": 0,
                "totalPlayerScore": 0,
                "totalScoreRank": 0,
                "playerScore0": 0,
                "playerScore1": 0,
                "playerScore2": 0,
                "playerScore3": 0,
                "playerScore4": 0,
                "playerScore5": 0,
                "playerScore6": 0,
                "playerScore7": 0,
                "playerScore8": 0,
                "playerScore9": 0,
                "perk0": 8439,
                "perk0Var1": 262,
                "perk0Var2": 0,
                "perk0Var3": 0,
                "perk1": 8446,
                "perk1Var1": 343,
                "perk1Var2": 0,
                "perk1Var3": 0,
                "perk2": 8473,
                "perk2Var1": 616,
                "perk2Var2": 0,
                "perk2Var3": 0,
                "perk3": 8242,
                "perk3Var1": 5,
                "perk3Var2": 0,
                "perk3Var3": 0,
                "perk4": 8304,
                "perk4Var1": 10,
                "perk4Var2": 0,
                "perk4Var3": 0,
                "perk5": 8347,
                "perk5Var1": 0,
                "perk5Var2": 0,
                "perk5Var3": 0,
                "perkPrimaryStyle": 8400,
                "perkSubStyle": 8300,
                "statPerk0": 5007,
                "statPerk1": 5002,
                "statPerk2": 5002
            },
            "timeline": {
                "participantId": 10,
                "creepsPerMinDeltas": {
                    "10-20": 1.6,
                    "0-10": 0.7
                },
                "xpPerMinDeltas": {
                    "10-20": 326.4,
                    "0-10": 148.39999999999998
                },
                "goldPerMinDeltas": {
                    "10-20": 189.8,
                    "0-10": 127.60000000000001
                },
                "csDiffPerMinDeltas": {
                    "10-20": 0.7000000000000002,
                    "0-10": 0
                },
                "xpDiffPerMinDeltas": {
                    "10-20": 59.80000000000004,
                    "0-10": -123.49999999999999
                },
                "damageTakenPerMinDeltas": {
                    "10-20": 735.4,
                    "0-10": 486.1
                },
                "damageTakenDiffPerMinDeltas": {
                    "10-20": -134.10000000000002,
                    "0-10": 103.4
                },
                "role": "DUO_SUPPORT",
                "lane": "BOTTOM"
            }
        }
    ],
    "participantIdentities": [
        {
            "participantId": 1,
            "name": "Aksynial"
        },
        {
            "participantId": 2,
            "name": "Williamxc"
        },
        {
            "participantId": 3,
            "name": "Shooeye"
        },
        {
            "participantId": 4,
            "name": "lgnore"
        },
        {
            "participantId": 5,
            "name": "BladesVengeance"
        },
        {
            "participantId": 6,
            "name": "Mooogen"
        },
        {
            "participantId": 7,
            "name": "Torpuddo"
        },
        {
            "participantId": 8,
            "name": "DrManMilk"
        },
        {
            "participantId": 9,
            "name": "Raphib737"
        },
        {
            "participantId": 10,
            "name": "Cha Siu Bill"
        }
    ]
}