{
  "gameId": 3174479500,
  "platformId": "NA1",
  "gameCreation": 1571279173059,
  "gameDuration": 2006,
  "queueId": 0,
  "mapId": 11,
  "seasonId": 13,
  "gameVersion": "9.20.292.2452",
  "gameMode": "CLASSIC",
  "gameType": "CUSTOM_GAME",
  "teams": [
    {
      "teamId": 100,
      "win": "Win",
      "firstBlood": true,
      "firstTower": true,
      "firstInhibitor": true,
      "firstBaron": true,
      "firstDragon": true,
      "firstRiftHerald": true,
      "towerKills": 11,
      "inhibitorKills": 3,
      "baronKills": 2,
      "dragonKills": 5,
      "vilemawKills": 0,
      "riftHeraldKills": 1,
      "dominionVictoryScore": 0,
      "bans": [
        {
          "championId": 131,
          "pickTurn": 1
        },
        {
          "championId": 96,
          "pickTurn": 3
        },
        {
          "championId": 75,
          "pickTurn": 5
        },
        {
          "championId": 50,
          "pickTurn": 2
        },
        {
          "championId": 245,
          "pickTurn": 4
        }
      ]
    },
    {
      "teamId": 200,
      "win": "Fail",
      "firstBlood": false,
      "firstTower": false,
      "firstInhibitor": false,
      "firstBaron": false,
      "firstDragon": false,
      "firstRiftHerald": false,
      "towerKills": 2,
      "inhibitorKills": 0,
      "baronKills": 0,
      "dragonKills": 0,
      "vilemawKills": 0,
      "riftHeraldKills": 0,
      "dominionVictoryScore": 0,
      "bans": [
        {
          "championId": 59,
          "pickTurn": 2
        },
        {
          "championId": 36,
          "pickTurn": 4
        },
        {
          "championId": 154,
          "pickTurn": 6
        },
        {
          "championId": 53,
          "pickTurn": 1
        },
        {
          "championId": 111,
          "pickTurn": 3
        }
      ]
    }
  ],
  "participants": [
    {
      "participantId": 1,
      "teamId": 100,
      "championId": 498,
      "spell1Id": 7,
      "spell2Id": 4,
      "stats": {
        "participantId": 1,
        "win": true,
        "item0": 3153,
        "item1": 3508,
        "item2": 3046,
        "item3": 3155,
        "item4": 3006,
        "item5": 3031,
        "item6": 3363,
        "kills": 11,
        "deaths": 2,
        "assists": 11,
        "largestKillingSpree": 4,
        "largestMultiKill": 2,
        "killingSprees": 3,
        "longestTimeSpentLiving": 786,
        "doubleKills": 2,
        "tripleKills": 0,
        "quadraKills": 0,
        "pentaKills": 0,
        "unrealKills": 0,
        "totalDamageDealt": 214042,
        "magicDamageDealt": 68,
        "physicalDamageDealt": 209753,
        "trueDamageDealt": 4221,
        "largestCriticalStrike": 964,
        "totalDamageDealtToChampions": 27153,
        "magicDamageDealtToChampions": 68,
        "physicalDamageDealtToChampions": 26898,
        "trueDamageDealtToChampions": 187,
        "totalHeal": 2743,
        "totalUnitsHealed": 4,
        "damageSelfMitigated": 7510,
        "damageDealtToObjectives": 33345,
        "damageDealtToTurrets": 6108,
        "visionScore": 34,
        "timeCCingOthers": 19,
        "totalDamageTaken": 12489,
        "magicalDamageTaken": 6280,
        "physicalDamageTaken": 6008,
        "trueDamageTaken": 200,
        "goldEarned": 16860,
        "goldSpent": 15550,
        "turretKills": 2,
        "inhibitorKills": 0,
        "totalMinionsKilled": 210,
        "neutralMinionsKilled": 28,
        "neutralMinionsKilledTeamJungle": 12,
        "neutralMinionsKilledEnemyJungle": 4,
        "totalTimeCrowdControlDealt": 41,
        "champLevel": 16,
        "visionWardsBoughtInGame": 2,
        "sightWardsBoughtInGame": 0,
        "wardsPlaced": 11,
        "wardsKilled": 7,
        "firstBloodKill": false,
        "firstBloodAssist": false,
        "firstTowerKill": false,
        "firstTowerAssist": false,
        "firstInhibitorKill": false,
        "firstInhibitorAssist": true,
        "combatPlayerScore": 0,
        "objectivePlayerScore": 0,
        "totalPlayerScore": 0,
        "totalScoreRank": 0,
        "playerScore0": 0,
        "playerScore1": 0,
        "playerScore2": 0,
        "playerScore3": 0,
        "playerScore4": 0,
        "playerScore5": 0,
        "playerScore6": 0,
        "playerScore7": 0,
        "playerScore8": 0,
        "playerScore9": 0,
        "perk0": 8008,
        "perk0Var1": 2,
        "perk0Var2": 30,
        "perk0Var3": 0,
        "perk1": 9111,
        "perk1Var1": 897,
        "perk1Var2": 440,
        "perk1Var3": 0,
        "perk2": 9104,
        "perk2Var1": 12,
        "perk2Var2": 0,
        "perk2Var3": 0,
        "perk3": 8017,
        "perk3Var1": 425,
        "perk3Var2": 0,
        "perk3Var3": 0,
        "perk4": 8304,
        "perk4Var1": 9,
        "perk4Var2": 0,
        "perk4Var3": 0,
        "perk5": 8345,
        "perk5Var1": 3,
        "perk5Var2": 0,
        "perk5Var3": 0,
        "perkPrimaryStyle": 8000,
        "perkSubStyle": 8300,
        "statPerk0": 5005,
        "statPerk1": 5008,
        "statPerk2": 5002
      },
      "timeline": {
        "participantId": 1,
        "creepsPerMinDeltas": {
          "10-20": 7.4,
          "0-10": 7.300000000000001,
          "20-30": 5.7
        },
        "xpPerMinDeltas": {
          "10-20": 472.4,
          "0-10": 350,
          "20-30": 516.2
        },
        "goldPerMinDeltas": {
          "10-20": 600,
          "0-10": 342.6,
          "20-30": 503.6
        },
        "csDiffPerMinDeltas": {
          "10-20": 0.95,
          "0-10": 0.4999999999999998,
          "20-30": -0.9500000000000002
        },
        "xpDiffPerMinDeltas": {
          "10-20": 38.45000000000002,
          "0-10": 57.30000000000001,
          "20-30": 46.80000000000001
        },
        "damageTakenPerMinDeltas": {
          "10-20": 286.5,
          "0-10": 281.8,
          "20-30": 511.4
        },
        "damageTakenDiffPerMinDeltas": {
          "10-20": 71.14999999999998,
          "0-10": -65.60000000000002,
          "20-30": 154.09999999999997
        },
        "role": "DUO_CARRY",
        "lane": "BOTTOM"
      }
    },
    {
      "participantId": 2,
      "teamId": 100,
      "championId": 236,
      "spell1Id": 3,
      "spell2Id": 4,
      "stats": {
        "participantId": 2,
        "win": true,
        "item0": 3031,
        "item1": 3153,
        "item2": 0,
        "item3": 3111,
        "item4": 3508,
        "item5": 0,
        "item6": 3363,
        "kills": 3,
        "deaths": 2,
        "assists": 10,
        "largestKillingSpree": 3,
        "largestMultiKill": 2,
        "killingSprees": 1,
        "longestTimeSpentLiving": 832,
        "doubleKills": 1,
        "tripleKills": 0,
        "quadraKills": 0,
        "pentaKills": 0,
        "unrealKills": 0,
        "totalDamageDealt": 196498,
        "magicDamageDealt": 6261,
        "physicalDamageDealt": 184020,
        "trueDamageDealt": 6216,
        "largestCriticalStrike": 1124,
        "totalDamageDealtToChampions": 13613,
        "magicDamageDealtToChampions": 679,
        "physicalDamageDealtToChampions": 12391,
        "trueDamageDealtToChampions": 543,
        "totalHeal": 3205,
        "totalUnitsHealed": 1,
        "damageSelfMitigated": 9997,
        "damageDealtToObjectives": 15312,
        "damageDealtToTurrets": 3228,
        "visionScore": 37,
        "timeCCingOthers": 4,
        "totalDamageTaken": 17903,
        "magicalDamageTaken": 8476,
        "physicalDamageTaken": 8858,
        "trueDamageTaken": 567,
        "goldEarned": 12952,
        "goldSpent": 11650,
        "turretKills": 1,
        "inhibitorKills": 0,
        "totalMinionsKilled": 194,
        "neutralMinionsKilled": 46,
        "neutralMinionsKilledTeamJungle": 40,
        "neutralMinionsKilledEnemyJungle": 2,
        "totalTimeCrowdControlDealt": 69,
        "champLevel": 17,
        "visionWardsBoughtInGame": 8,
        "sightWardsBoughtInGame": 0,
        "wardsPlaced": 19,
        "wardsKilled": 3,
        "firstBloodKill": false,
        "firstBloodAssist": false,
        "firstTowerKill": false,
        "firstTowerAssist": false,
        "firstInhibitorKill": false,
        "firstInhibitorAssist": true,
        "combatPlayerScore": 0,
        "objectivePlayerScore": 0,
        "totalPlayerScore": 0,
        "totalScoreRank": 0,
        "playerScore0": 0,
        "playerScore1": 0,
        "playerScore2": 0,
        "playerScore3": 0,
        "playerScore4": 0,
        "playerScore5": 0,
        "playerScore6": 0,
        "playerScore7": 0,
        "playerScore8": 0,
        "playerScore9": 0,
        "perk0": 8005,
        "perk0Var1": 1342,
        "perk0Var2": 638,
        "perk0Var3": 704,
        "perk1": 9111,
        "perk1Var1": 899,
        "perk1Var2": 260,
        "perk1Var3": 0,
        "perk2": 9103,
        "perk2Var1": 28,
        "perk2Var2": 50,
        "perk2Var3": 0,
        "perk3": 8014,
        "perk3Var1": 307,
        "perk3Var2": 0,
        "perk3Var3": 0,
        "perk4": 8304,
        "perk4Var1": 12,
        "perk4Var2": 0,
        "perk4Var3": 0,
        "perk5": 8345,
        "perk5Var1": 3,
        "perk5Var2": 0,
        "perk5Var3": 0,
        "perkPrimaryStyle": 8000,
        "perkSubStyle": 8300,
        "statPerk0": 5005,
        "statPerk1": 5008,
        "statPerk2": 5002
      },
      "timeline": {
        "participantId": 2,
        "creepsPerMinDeltas": {
          "10-20": 5.9,
          "0-10": 7.5,
          "20-30": 4.8
        },
        "xpPerMinDeltas": {
          "10-20": 403.20000000000005,
          "0-10": 476.6,
          "20-30": 570.2
        },
        "goldPerMinDeltas": {
          "10-20": 308.70000000000005,
          "0-10": 256.20000000000005,
          "20-30": 438.6
        },
        "damageTakenPerMinDeltas": {
          "10-20": 761.1,
          "0-10": 190.1,
          "20-30": 624.8
        },
        "role": "DUO",
        "lane": "MIDDLE"
      }
    },
    {
      "participantId": 3,
      "teamId": 100,
      "championId": 10,
      "spell1Id": 4,
      "spell2Id": 12,
      "stats": {
        "participantId": 3,
        "win": true,
        "item0": 3006,
        "item1": 2033,
        "item2": 3146,
        "item3": 3115,
        "item4": 3124,
        "item5": 0,
        "item6": 3340,
        "kills": 5,
        "deaths": 4,
        "assists": 11,
        "largestKillingSpree": 2,
        "largestMultiKill": 1,
        "killingSprees": 2,
        "longestTimeSpentLiving": 559,
        "doubleKills": 0,
        "tripleKills": 0,
        "quadraKills": 0,
        "pentaKills": 0,
        "unrealKills": 0,
        "totalDamageDealt": 141956,
        "magicDamageDealt": 82302,
        "physicalDamageDealt": 45142,
        "trueDamageDealt": 14511,
        "largestCriticalStrike": 0,
        "totalDamageDealtToChampions": 10829,
        "magicDamageDealtToChampions": 7465,
        "physicalDamageDealtToChampions": 3302,
        "trueDamageDealtToChampions": 61,
        "totalHeal": 5293,
        "totalUnitsHealed": 5,
        "damageSelfMitigated": 8320,
        "damageDealtToObjectives": 14636,
        "damageDealtToTurrets": 5338,
        "visionScore": 34,
        "timeCCingOthers": 5,
        "totalDamageTaken": 17378,
        "magicalDamageTaken": 6945,
        "physicalDamageTaken": 9968,
        "trueDamageTaken": 463,
        "goldEarned": 13645,
        "goldSpent": 11100,
        "turretKills": 2,
        "inhibitorKills": 1,
        "totalMinionsKilled": 170,
        "neutralMinionsKilled": 16,
        "neutralMinionsKilledTeamJungle": 0,
        "neutralMinionsKilledEnemyJungle": 2,
        "totalTimeCrowdControlDealt": 188,
        "champLevel": 16,
        "visionWardsBoughtInGame": 0,
        "sightWardsBoughtInGame": 0,
        "wardsPlaced": 8,
        "wardsKilled": 12,
        "firstBloodKill": false,
        "firstBloodAssist": false,
        "firstTowerKill": false,
        "firstTowerAssist": true,
        "firstInhibitorKill": false,
        "firstInhibitorAssist": false,
        "combatPlayerScore": 0,
        "objectivePlayerScore": 0,
        "totalPlayerScore": 0,
        "totalScoreRank": 0,
        "playerScore0": 0,
        "playerScore1": 0,
        "playerScore2": 0,
        "playerScore3": 0,
        "playerScore4": 0,
        "playerScore5": 0,
        "playerScore6": 0,
        "playerScore7": 0,
        "playerScore8": 0,
        "playerScore9": 0,
        "perk0": 8008,
        "perk0Var1": 1,
        "perk0Var2": 30,
        "perk0Var3": 0,
        "perk1": 9111,
        "perk1Var1": 738,
        "perk1Var2": 320,
        "perk1Var3": 0,
        "perk2": 9104,
        "perk2Var1": 18,
        "perk2Var2": 0,
        "perk2Var3": 0,
        "perk3": 8014,
        "perk3Var1": 344,
        "perk3Var2": 0,
        "perk3Var3": 0,
        "perk4": 8473,
        "perk4Var1": 532,
        "perk4Var2": 0,
        "perk4Var3": 0,
        "perk5": 8451,
        "perk5Var1": 185,
        "perk5Var2": 0,
        "perk5Var3": 0,
        "perkPrimaryStyle": 8000,
        "perkSubStyle": 8400,
        "statPerk0": 5005,
        "statPerk1": 5008,
        "statPerk2": 5002
      },
      "timeline": {
        "participantId": 3,
        "creepsPerMinDeltas": {
          "10-20": 5.4,
          "0-10": 4.9,
          "20-30": 4.6000000000000005
        },
        "xpPerMinDeltas": {
          "10-20": 398.3,
          "0-10": 388.5,
          "20-30": 515.4
        },
        "goldPerMinDeltas": {
          "10-20": 427.4,
          "0-10": 244.6,
          "20-30": 434.3
        },
        "damageTakenPerMinDeltas": {
          "10-20": 610.7,
          "0-10": 369.1,
          "20-30": 654
        },
        "role": "DUO",
        "lane": "TOP"
      }
    },
    {
      "participantId": 4,
      "teamId": 100,
      "championId": 412,
      "spell1Id": 4,
      "spell2Id": 14,
      "stats": {
        "participantId": 4,
        "win": true,
        "item0": 3069,
        "item1": 3109,
        "item2": 3107,
        "item3": 2065,
        "item4": 3117,
        "item5": 0,
        "item6": 3364,
        "kills": 5,
        "deaths": 4,
        "assists": 17,
        "largestKillingSpree": 2,
        "largestMultiKill": 1,
        "killingSprees": 1,
        "longestTimeSpentLiving": 832,
        "doubleKills": 0,
        "tripleKills": 0,
        "quadraKills": 0,
        "pentaKills": 0,
        "unrealKills": 0,
        "totalDamageDealt": 21179,
        "magicDamageDealt": 12106,
        "physicalDamageDealt": 7780,
        "trueDamageDealt": 1292,
        "largestCriticalStrike": 0,
        "totalDamageDealtToChampions": 8602,
        "magicDamageDealtToChampions": 6072,
        "physicalDamageDealtToChampions": 1487,
        "trueDamageDealtToChampions": 1042,
        "totalHeal": 3818,
        "totalUnitsHealed": 5,
        "damageSelfMitigated": 13240,
        "damageDealtToObjectives": 7412,
        "damageDealtToTurrets": 1123,
        "visionScore": 97,
        "timeCCingOthers": 28,
        "totalDamageTaken": 18800,
        "magicalDamageTaken": 8060,
        "physicalDamageTaken": 9550,
        "trueDamageTaken": 1189,
        "goldEarned": 10579,
        "goldSpent": 9775,
        "turretKills": 0,
        "inhibitorKills": 0,
        "totalMinionsKilled": 19,
        "neutralMinionsKilled": 0,
        "neutralMinionsKilledTeamJungle": 0,
        "neutralMinionsKilledEnemyJungle": 0,
        "totalTimeCrowdControlDealt": 92,
        "champLevel": 14,
        "visionWardsBoughtInGame": 9,
        "sightWardsBoughtInGame": 0,
        "wardsPlaced": 34,
        "wardsKilled": 14,
        "firstBloodKill": true,
        "firstBloodAssist": false,
        "firstTowerKill": false,
        "firstTowerAssist": false,
        "firstInhibitorKill": false,
        "firstInhibitorAssist": false,
        "combatPlayerScore": 0,
        "objectivePlayerScore": 0,
        "totalPlayerScore": 0,
        "totalScoreRank": 0,
        "playerScore0": 0,
        "playerScore1": 0,
        "playerScore2": 0,
        "playerScore3": 0,
        "playerScore4": 0,
        "playerScore5": 0,
        "playerScore6": 0,
        "playerScore7": 0,
        "playerScore8": 0,
        "playerScore9": 0,
        "perk0": 8437,
        "perk0Var1": 240,
        "perk0Var2": 193,
        "perk0Var3": 0,
        "perk1": 8463,
        "perk1Var1": 2720,
        "perk1Var2": 0,
        "perk1Var3": 0,
        "perk2": 8473,
        "perk2Var1": 334,
        "perk2Var2": 0,
        "perk2Var3": 0,
        "perk3": 8451,
        "perk3Var1": 167,
        "perk3Var2": 0,
        "perk3Var3": 0,
        "perk4": 8143,
        "perk4Var1": 81,
        "perk4Var2": 0,
        "perk4Var3": 0,
        "perk5": 8120,
        "perk5Var1": 5,
        "perk5Var2": 30,
        "perk5Var3": 14,
        "perkPrimaryStyle": 8400,
        "perkSubStyle": 8100,
        "statPerk0": 5008,
        "statPerk1": 5003,
        "statPerk2": 5002
      },
      "timeline": {
        "participantId": 4,
        "creepsPerMinDeltas": {
          "10-20": 0.5,
          "0-10": 0.6,
          "20-30": 0.6000000000000001
        },
        "xpPerMinDeltas": {
          "10-20": 260.9,
          "0-10": 317,
          "20-30": 341.3
        },
        "goldPerMinDeltas": {
          "10-20": 295.9,
          "0-10": 279.3,
          "20-30": 283.5
        },
        "csDiffPerMinDeltas": {
          "10-20": 0.95,
          "0-10": 0.4999999999999998,
          "20-30": -0.9500000000000002
        },
        "xpDiffPerMinDeltas": {
          "10-20": 38.45000000000002,
          "0-10": 57.30000000000001,
          "20-30": 46.80000000000001
        },
        "damageTakenPerMinDeltas": {
          "10-20": 704.4,
          "0-10": 218.8,
          "20-30": 677.1
        },
        "damageTakenDiffPerMinDeltas": {
          "10-20": 71.14999999999998,
          "0-10": -65.60000000000002,
          "20-30": 154.09999999999997
        },
        "role": "DUO_SUPPORT",
        "lane": "BOTTOM"
      }
    },
    {
      "participantId": 5,
      "teamId": 100,
      "championId": 106,
      "spell1Id": 11,
      "spell2Id": 4,
      "stats": {
        "participantId": 5,
        "win": true,
        "item0": 3065,
        "item1": 1401,
        "item2": 1028,
        "item3": 3111,
        "item4": 3742,
        "item5": 3052,
        "item6": 3364,
        "kills": 7,
        "deaths": 3,
        "assists": 12,
        "largestKillingSpree": 4,
        "largestMultiKill": 1,
        "killingSprees": 2,
        "longestTimeSpentLiving": 1018,
        "doubleKills": 0,
        "tripleKills": 0,
        "quadraKills": 0,
        "pentaKills": 0,
        "unrealKills": 0,
        "totalDamageDealt": 132538,
        "magicDamageDealt": 46398,
        "physicalDamageDealt": 72903,
        "trueDamageDealt": 13237,
        "largestCriticalStrike": 0,
        "totalDamageDealtToChampions": 9195,
        "magicDamageDealtToChampions": 4253,
        "physicalDamageDealtToChampions": 3896,
        "trueDamageDealtToChampions": 1045,
        "totalHeal": 11333,
        "totalUnitsHealed": 1,
        "damageSelfMitigated": 33206,
        "damageDealtToObjectives": 37654,
        "damageDealtToTurrets": 4377,
        "visionScore": 41,
        "timeCCingOthers": 25,
        "totalDamageTaken": 34646,
        "magicalDamageTaken": 9265,
        "physicalDamageTaken": 20523,
        "trueDamageTaken": 4857,
        "goldEarned": 13352,
        "goldSpent": 11575,
        "turretKills": 3,
        "inhibitorKills": 2,
        "totalMinionsKilled": 33,
        "neutralMinionsKilled": 102,
        "neutralMinionsKilledTeamJungle": 42,
        "neutralMinionsKilledEnemyJungle": 9,
        "totalTimeCrowdControlDealt": 621,
        "champLevel": 16,
        "visionWardsBoughtInGame": 7,
        "sightWardsBoughtInGame": 0,
        "wardsPlaced": 8,
        "wardsKilled": 6,
        "firstBloodKill": false,
        "firstBloodAssist": false,
        "firstTowerKill": true,
        "firstTowerAssist": false,
        "firstInhibitorKill": true,
        "firstInhibitorAssist": false,
        "combatPlayerScore": 0,
        "objectivePlayerScore": 0,
        "totalPlayerScore": 0,
        "totalScoreRank": 0,
        "playerScore0": 0,
        "playerScore1": 0,
        "playerScore2": 0,
        "playerScore3": 0,
        "playerScore4": 0,
        "playerScore5": 0,
        "playerScore6": 0,
        "playerScore7": 0,
        "playerScore8": 0,
        "playerScore9": 0,
        "perk0": 8439,
        "perk0Var1": 441,
        "perk0Var2": 0,
        "perk0Var3": 0,
        "perk1": 8446,
        "perk1Var1": 1808,
        "perk1Var2": 0,
        "perk1Var3": 0,
        "perk2": 8429,
        "perk2Var1": 70,
        "perk2Var2": 17,
        "perk2Var3": 15,
        "perk3": 8453,
        "perk3Var1": 1073,
        "perk3Var2": 47,
        "perk3Var3": 0,
        "perk4": 9111,
        "perk4Var1": 2311,
        "perk4Var2": 380,
        "perk4Var3": 0,
        "perk5": 9104,
        "perk5Var1": 12,
        "perk5Var2": 50,
        "perk5Var3": 0,
        "perkPrimaryStyle": 8400,
        "perkSubStyle": 8000,
        "statPerk0": 5005,
        "statPerk1": 5008,
        "statPerk2": 5002
      },
      "timeline": {
        "participantId": 5,
        "creepsPerMinDeltas": {
          "10-20": 0.8999999999999999,
          "0-10": 1,
          "20-30": 1.1
        },
        "xpPerMinDeltas": {
          "10-20": 375.4,
          "0-10": 333,
          "20-30": 534.9
        },
        "goldPerMinDeltas": {
          "10-20": 413.8,
          "0-10": 311.6,
          "20-30": 405.79999999999995
        },
        "damageTakenPerMinDeltas": {
          "10-20": 1119.3,
          "0-10": 447.1,
          "20-30": 1267.4
        },
        "role": "NONE",
        "lane": "JUNGLE"
      }
    },
    {
      "participantId": 6,
      "teamId": 200,
      "championId": 51,
      "spell1Id": 4,
      "spell2Id": 7,
      "stats": {
        "participantId": 6,
        "win": false,
        "item0": 3006,
        "item1": 3087,
        "item2": 3094,
        "item3": 0,
        "item4": 3031,
        "item5": 3123,
        "item6": 3340,
        "kills": 3,
        "deaths": 5,
        "assists": 5,
        "largestKillingSpree": 2,
        "largestMultiKill": 1,
        "killingSprees": 1,
        "longestTimeSpentLiving": 887,
        "doubleKills": 0,
        "tripleKills": 0,
        "quadraKills": 0,
        "pentaKills": 0,
        "unrealKills": 0,
        "totalDamageDealt": 171004,
        "magicDamageDealt": 5167,
        "physicalDamageDealt": 159576,
        "trueDamageDealt": 6260,
        "largestCriticalStrike": 974,
        "totalDamageDealtToChampions": 14102,
        "magicDamageDealtToChampions": 651,
        "physicalDamageDealtToChampions": 13006,
        "trueDamageDealtToChampions": 444,
        "totalHeal": 3083,
        "totalUnitsHealed": 3,
        "damageSelfMitigated": 10221,
        "damageDealtToObjectives": 3244,
        "damageDealtToTurrets": 2884,
        "visionScore": 19,
        "timeCCingOthers": 23,
        "totalDamageTaken": 17892,
        "magicalDamageTaken": 2566,
        "physicalDamageTaken": 14835,
        "trueDamageTaken": 490,
        "goldEarned": 11658,
        "goldSpent": 11200,
        "turretKills": 2,
        "inhibitorKills": 0,
        "totalMinionsKilled": 203,
        "neutralMinionsKilled": 15,
        "neutralMinionsKilledTeamJungle": 15,
        "neutralMinionsKilledEnemyJungle": 0,
        "totalTimeCrowdControlDealt": 73,
        "champLevel": 15,
        "visionWardsBoughtInGame": 3,
        "sightWardsBoughtInGame": 0,
        "wardsPlaced": 12,
        "wardsKilled": 5,
        "firstBloodKill": false,
        "firstBloodAssist": false,
        "firstTowerKill": false,
        "firstTowerAssist": false,
        "firstInhibitorKill": false,
        "firstInhibitorAssist": false,
        "combatPlayerScore": 0,
        "objectivePlayerScore": 0,
        "totalPlayerScore": 0,
        "totalScoreRank": 0,
        "playerScore0": 0,
        "playerScore1": 0,
        "playerScore2": 0,
        "playerScore3": 0,
        "playerScore4": 0,
        "playerScore5": 0,
        "playerScore6": 0,
        "playerScore7": 0,
        "playerScore8": 0,
        "playerScore9": 0,
        "perk0": 8021,
        "perk0Var1": 1332,
        "perk0Var2": 0,
        "perk0Var3": 0,
        "perk1": 9111,
        "perk1Var1": 278,
        "perk1Var2": 160,
        "perk1Var3": 0,
        "perk2": 9103,
        "perk2Var1": 0,
        "perk2Var2": 0,
        "perk2Var3": 0,
        "perk3": 8014,
        "perk3Var1": 219,
        "perk3Var2": 0,
        "perk3Var3": 0,
        "perk4": 8304,
        "perk4Var1": 11,
        "perk4Var2": 1,
        "perk4Var3": 5,
        "perk5": 8345,
        "perk5Var1": 3,
        "perk5Var2": 0,
        "perk5Var3": 0,
        "perkPrimaryStyle": 8000,
        "perkSubStyle": 8300,
        "statPerk0": 5005,
        "statPerk1": 5008,
        "statPerk2": 5002
      },
      "timeline": {
        "participantId": 6,
        "creepsPerMinDeltas": {
          "10-20": 4.5,
          "0-10": 5.6,
          "20-30": 6.9
        },
        "xpPerMinDeltas": {
          "10-20": 370,
          "0-10": 279.5,
          "20-30": 445.8
        },
        "goldPerMinDeltas": {
          "10-20": 362,
          "0-10": 244.2,
          "20-30": 368.20000000000005
        },
        "csDiffPerMinDeltas": {
          "10-20": -0.95,
          "0-10": -0.4999999999999998,
          "20-30": 0.9500000000000002
        },
        "xpDiffPerMinDeltas": {
          "10-20": -38.45000000000002,
          "0-10": -57.30000000000001,
          "20-30": -46.80000000000001
        },
        "damageTakenPerMinDeltas": {
          "10-20": 542.8,
          "0-10": 330.8,
          "20-30": 537.2
        },
        "damageTakenDiffPerMinDeltas": {
          "10-20": -71.14999999999998,
          "0-10": 65.60000000000002,
          "20-30": -154.09999999999997
        },
        "role": "DUO_CARRY",
        "lane": "BOTTOM"
      }
    },
    {
      "participantId": 7,
      "teamId": 200,
      "championId": 157,
      "spell1Id": 12,
      "spell2Id": 4,
      "stats": {
        "participantId": 7,
        "win": false,
        "item0": 3053,
        "item1": 3031,
        "item2": 3046,
        "item3": 3006,
        "item4": 0,
        "item5": 0,
        "item6": 3363,
        "kills": 4,
        "deaths": 9,
        "assists": 7,
        "largestKillingSpree": 0,
        "largestMultiKill": 1,
        "killingSprees": 0,
        "longestTimeSpentLiving": 314,
        "doubleKills": 0,
        "tripleKills": 0,
        "quadraKills": 0,
        "pentaKills": 0,
        "unrealKills": 0,
        "totalDamageDealt": 217183,
        "magicDamageDealt": 19423,
        "physicalDamageDealt": 175230,
        "trueDamageDealt": 22529,
        "largestCriticalStrike": 636,
        "totalDamageDealtToChampions": 17069,
        "magicDamageDealtToChampions": 1496,
        "physicalDamageDealtToChampions": 13798,
        "trueDamageDealtToChampions": 1775,
        "totalHeal": 4302,
        "totalUnitsHealed": 1,
        "damageSelfMitigated": 26781,
        "damageDealtToObjectives": 4968,
        "damageDealtToTurrets": 1476,
        "visionScore": 14,
        "timeCCingOthers": 30,
        "totalDamageTaken": 27143,
        "magicalDamageTaken": 8523,
        "physicalDamageTaken": 17909,
        "trueDamageTaken": 710,
        "goldEarned": 11998,
        "goldSpent": 11475,
        "turretKills": 0,
        "inhibitorKills": 0,
        "totalMinionsKilled": 193,
        "neutralMinionsKilled": 23,
        "neutralMinionsKilledTeamJungle": 19,
        "neutralMinionsKilledEnemyJungle": 0,
        "totalTimeCrowdControlDealt": 243,
        "champLevel": 16,
        "visionWardsBoughtInGame": 3,
        "sightWardsBoughtInGame": 0,
        "wardsPlaced": 12,
        "wardsKilled": 1,
        "firstBloodKill": false,
        "firstBloodAssist": false,
        "firstTowerKill": false,
        "firstTowerAssist": false,
        "firstInhibitorKill": false,
        "firstInhibitorAssist": false,
        "combatPlayerScore": 0,
        "objectivePlayerScore": 0,
        "totalPlayerScore": 0,
        "totalScoreRank": 0,
        "playerScore0": 0,
        "playerScore1": 0,
        "playerScore2": 0,
        "playerScore3": 0,
        "playerScore4": 0,
        "playerScore5": 0,
        "playerScore6": 0,
        "playerScore7": 0,
        "playerScore8": 0,
        "playerScore9": 0,
        "perk0": 8010,
        "perk0Var1": 939,
        "perk0Var2": 432,
        "perk0Var3": 961,
        "perk1": 9111,
        "perk1Var1": 956,
        "perk1Var2": 220,
        "perk1Var3": 0,
        "perk2": 9104,
        "perk2Var1": 16,
        "perk2Var2": 50,
        "perk2Var3": 0,
        "perk3": 8014,
        "perk3Var1": 249,
        "perk3Var2": 0,
        "perk3Var3": 0,
        "perk4": 8135,
        "perk4Var1": 2116,
        "perk4Var2": 5,
        "perk4Var3": 0,
        "perk5": 8139,
        "perk5Var1": 767,
        "perk5Var2": 0,
        "perk5Var3": 0,
        "perkPrimaryStyle": 8000,
        "perkSubStyle": 8100,
        "statPerk0": 5005,
        "statPerk1": 5008,
        "statPerk2": 5002
      },
      "timeline": {
        "participantId": 7,
        "creepsPerMinDeltas": {
          "10-20": 4.699999999999999,
          "0-10": 5.300000000000001,
          "20-30": 7.199999999999999
        },
        "xpPerMinDeltas": {
          "10-20": 534.7,
          "0-10": 410.5,
          "20-30": 486.3
        },
        "goldPerMinDeltas": {
          "10-20": 387.4,
          "0-10": 236.9,
          "20-30": 349
        },
        "damageTakenPerMinDeltas": {
          "10-20": 1075.5,
          "0-10": 408.5,
          "20-30": 869.2
        },
        "role": "NONE",
        "lane": "TOP"
      }
    },
    {
      "participantId": 8,
      "teamId": 200,
      "championId": 101,
      "spell1Id": 4,
      "spell2Id": 14,
      "stats": {
        "participantId": 8,
        "win": false,
        "item0": 3096,
        "item1": 3158,
        "item2": 2055,
        "item3": 3285,
        "item4": 1058,
        "item5": 1058,
        "item6": 3364,
        "kills": 3,
        "deaths": 8,
        "assists": 4,
        "largestKillingSpree": 0,
        "largestMultiKill": 2,
        "killingSprees": 0,
        "longestTimeSpentLiving": 446,
        "doubleKills": 1,
        "tripleKills": 0,
        "quadraKills": 0,
        "pentaKills": 0,
        "unrealKills": 0,
        "totalDamageDealt": 60428,
        "magicDamageDealt": 53229,
        "physicalDamageDealt": 3356,
        "trueDamageDealt": 3843,
        "largestCriticalStrike": 0,
        "totalDamageDealtToChampions": 16625,
        "magicDamageDealtToChampions": 15028,
        "physicalDamageDealtToChampions": 474,
        "trueDamageDealtToChampions": 1123,
        "totalHeal": 393,
        "totalUnitsHealed": 1,
        "damageSelfMitigated": 5324,
        "damageDealtToObjectives": 900,
        "damageDealtToTurrets": 677,
        "visionScore": 46,
        "timeCCingOthers": 23,
        "totalDamageTaken": 12215,
        "magicalDamageTaken": 1825,
        "physicalDamageTaken": 10146,
        "trueDamageTaken": 244,
        "goldEarned": 9342,
        "goldSpent": 8300,
        "turretKills": 0,
        "inhibitorKills": 0,
        "totalMinionsKilled": 57,
        "neutralMinionsKilled": 0,
        "neutralMinionsKilledTeamJungle": 0,
        "neutralMinionsKilledEnemyJungle": 0,
        "totalTimeCrowdControlDealt": 150,
        "champLevel": 13,
        "visionWardsBoughtInGame": 10,
        "sightWardsBoughtInGame": 0,
        "wardsPlaced": 36,
        "wardsKilled": 4,
        "firstBloodKill": false,
        "firstBloodAssist": false,
        "firstTowerKill": false,
        "firstTowerAssist": false,
        "firstInhibitorKill": false,
        "firstInhibitorAssist": false,
        "combatPlayerScore": 0,
        "objectivePlayerScore": 0,
        "totalPlayerScore": 0,
        "totalScoreRank": 0,
        "playerScore0": 0,
        "playerScore1": 0,
        "playerScore2": 0,
        "playerScore3": 0,
        "playerScore4": 0,
        "playerScore5": 0,
        "playerScore6": 0,
        "playerScore7": 0,
        "playerScore8": 0,
        "playerScore9": 0,
        "perk0": 8229,
        "perk0Var1": 1344,
        "perk0Var2": 0,
        "perk0Var3": 0,
        "perk1": 8226,
        "perk1Var1": 250,
        "perk1Var2": 841,
        "perk1Var3": 0,
        "perk2": 8210,
        "perk2Var1": 20,
        "perk2Var2": 0,
        "perk2Var3": 0,
        "perk3": 8236,
        "perk3Var1": 48,
        "perk3Var2": 0,
        "perk3Var3": 0,
        "perk4": 8138,
        "perk4Var1": 14,
        "perk4Var2": 0,
        "perk4Var3": 0,
        "perk5": 8105,
        "perk5Var1": 13,
        "perk5Var2": 4,
        "perk5Var3": 0,
        "perkPrimaryStyle": 8200,
        "perkSubStyle": 8100,
        "statPerk0": 5008,
        "statPerk1": 5008,
        "statPerk2": 5001
      },
      "timeline": {
        "participantId": 8,
        "creepsPerMinDeltas": {
          "10-20": 1.5,
          "0-10": 1.3,
          "20-30": 1.3
        },
        "xpPerMinDeltas": {
          "10-20": 286.4,
          "0-10": 272.9,
          "20-30": 318.1
        },
        "goldPerMinDeltas": {
          "10-20": 289.1,
          "0-10": 183.3,
          "20-30": 306.6
        },
        "csDiffPerMinDeltas": {
          "10-20": -0.95,
          "0-10": -0.4999999999999998,
          "20-30": 0.9500000000000002
        },
        "xpDiffPerMinDeltas": {
          "10-20": -38.45000000000002,
          "0-10": -57.30000000000001,
          "20-30": -46.80000000000001
        },
        "damageTakenPerMinDeltas": {
          "10-20": 305.8,
          "0-10": 301,
          "20-30": 343.1
        },
        "damageTakenDiffPerMinDeltas": {
          "10-20": -71.14999999999998,
          "0-10": 65.60000000000002,
          "20-30": -154.09999999999997
        },
        "role": "DUO_SUPPORT",
        "lane": "BOTTOM"
      }
    },
    {
      "participantId": 9,
      "teamId": 200,
      "championId": 61,
      "spell1Id": 14,
      "spell2Id": 4,
      "stats": {
        "participantId": 9,
        "win": false,
        "item0": 3020,
        "item1": 3157,
        "item2": 3285,
        "item3": 3136,
        "item4": 0,
        "item5": 0,
        "item6": 3340,
        "kills": 1,
        "deaths": 2,
        "assists": 10,
        "largestKillingSpree": 0,
        "largestMultiKill": 1,
        "killingSprees": 0,
        "longestTimeSpentLiving": 1734,
        "doubleKills": 0,
        "tripleKills": 0,
        "quadraKills": 0,
        "pentaKills": 0,
        "unrealKills": 0,
        "totalDamageDealt": 100394,
        "magicDamageDealt": 88425,
        "physicalDamageDealt": 11605,
        "trueDamageDealt": 363,
        "largestCriticalStrike": 0,
        "totalDamageDealtToChampions": 15534,
        "magicDamageDealtToChampions": 14673,
        "physicalDamageDealtToChampions": 497,
        "trueDamageDealtToChampions": 363,
        "totalHeal": 780,
        "totalUnitsHealed": 1,
        "damageSelfMitigated": 9188,
        "damageDealtToObjectives": 1279,
        "damageDealtToTurrets": 1279,
        "visionScore": 12,
        "timeCCingOthers": 20,
        "totalDamageTaken": 10207,
        "magicalDamageTaken": 1887,
        "physicalDamageTaken": 8212,
        "trueDamageTaken": 108,
        "goldEarned": 9022,
        "goldSpent": 9025,
        "turretKills": 0,
        "inhibitorKills": 0,
        "totalMinionsKilled": 162,
        "neutralMinionsKilled": 0,
        "neutralMinionsKilledTeamJungle": 0,
        "neutralMinionsKilledEnemyJungle": 0,
        "totalTimeCrowdControlDealt": 337,
        "champLevel": 14,
        "visionWardsBoughtInGame": 1,
        "sightWardsBoughtInGame": 0,
        "wardsPlaced": 9,
        "wardsKilled": 2,
        "firstBloodKill": false,
        "firstBloodAssist": false,
        "firstTowerKill": false,
        "firstTowerAssist": false,
        "firstInhibitorKill": false,
        "firstInhibitorAssist": false,
        "combatPlayerScore": 0,
        "objectivePlayerScore": 0,
        "totalPlayerScore": 0,
        "totalScoreRank": 0,
        "playerScore0": 0,
        "playerScore1": 0,
        "playerScore2": 0,
        "playerScore3": 0,
        "playerScore4": 0,
        "playerScore5": 0,
        "playerScore6": 0,
        "playerScore7": 0,
        "playerScore8": 0,
        "playerScore9": 0,
        "perk0": 8229,
        "perk0Var1": 1630,
        "perk0Var2": 0,
        "perk0Var3": 0,
        "perk1": 8226,
        "perk1Var1": 250,
        "perk1Var2": 1399,
        "perk1Var3": 0,
        "perk2": 8210,
        "perk2Var1": 0,
        "perk2Var2": 0,
        "perk2Var3": 0,
        "perk3": 8236,
        "perk3Var1": 48,
        "perk3Var2": 0,
        "perk3Var3": 0,
        "perk4": 8313,
        "perk4Var1": 0,
        "perk4Var2": 0,
        "perk4Var3": 0,
        "perk5": 8345,
        "perk5Var1": 3,
        "perk5Var2": 0,
        "perk5Var3": 0,
        "perkPrimaryStyle": 8200,
        "perkSubStyle": 8300,
        "statPerk0": 5008,
        "statPerk1": 5002,
        "statPerk2": 5002
      },
      "timeline": {
        "participantId": 9,
        "creepsPerMinDeltas": {
          "10-20": 6.1,
          "0-10": 7.4,
          "20-30": 2
        },
        "xpPerMinDeltas": {
          "10-20": 415.20000000000005,
          "0-10": 469.59999999999997,
          "20-30": 254.6
        },
        "goldPerMinDeltas": {
          "10-20": 359.5,
          "0-10": 248.10000000000002,
          "20-30": 183.9
        },
        "damageTakenPerMinDeltas": {
          "10-20": 266.5,
          "0-10": 96.9,
          "20-30": 440.1
        },
        "role": "SOLO",
        "lane": "MIDDLE"
      }
    },
    {
      "participantId": 10,
      "teamId": 200,
      "championId": 12,
      "spell1Id": 4,
      "spell2Id": 11,
      "stats": {
        "participantId": 10,
        "win": false,
        "item0": 3077,
        "item1": 2031,
        "item2": 3109,
        "item3": 1401,
        "item4": 1011,
        "item5": 3117,
        "item6": 3340,
        "kills": 4,
        "deaths": 7,
        "assists": 7,
        "largestKillingSpree": 2,
        "largestMultiKill": 1,
        "killingSprees": 1,
        "longestTimeSpentLiving": 721,
        "doubleKills": 0,
        "tripleKills": 0,
        "quadraKills": 0,
        "pentaKills": 0,
        "unrealKills": 0,
        "totalDamageDealt": 91363,
        "magicDamageDealt": 42439,
        "physicalDamageDealt": 38102,
        "trueDamageDealt": 10820,
        "largestCriticalStrike": 0,
        "totalDamageDealtToChampions": 6850,
        "magicDamageDealtToChampions": 5079,
        "physicalDamageDealtToChampions": 1197,
        "trueDamageDealtToChampions": 574,
        "totalHeal": 11579,
        "totalUnitsHealed": 5,
        "damageSelfMitigated": 56934,
        "damageDealtToObjectives": 4966,
        "damageDealtToTurrets": 828,
        "visionScore": 31,
        "timeCCingOthers": 24,
        "totalDamageTaken": 30577,
        "magicalDamageTaken": 6505,
        "physicalDamageTaken": 22745,
        "trueDamageTaken": 1326,
        "goldEarned": 8983,
        "goldSpent": 8375,
        "turretKills": 0,
        "inhibitorKills": 0,
        "totalMinionsKilled": 27,
        "neutralMinionsKilled": 82,
        "neutralMinionsKilledTeamJungle": 75,
        "neutralMinionsKilledEnemyJungle": 0,
        "totalTimeCrowdControlDealt": 218,
        "champLevel": 13,
        "visionWardsBoughtInGame": 4,
        "sightWardsBoughtInGame": 0,
        "wardsPlaced": 15,
        "wardsKilled": 8,
        "firstBloodKill": false,
        "firstBloodAssist": false,
        "firstTowerKill": false,
        "firstTowerAssist": false,
        "firstInhibitorKill": false,
        "firstInhibitorAssist": false,
        "combatPlayerScore": 0,
        "objectivePlayerScore": 0,
        "totalPlayerScore": 0,
        "totalScoreRank": 0,
        "playerScore0": 0,
        "playerScore1": 0,
        "playerScore2": 0,
        "playerScore3": 0,
        "playerScore4": 0,
        "playerScore5": 0,
        "playerScore6": 0,
        "playerScore7": 0,
        "playerScore8": 0,
        "playerScore9": 0,
        "perk0": 8439,
        "perk0Var1": 1126,
        "perk0Var2": 0,
        "perk0Var3": 0,
        "perk1": 8463,
        "perk1Var1": 405,
        "perk1Var2": 0,
        "perk1Var3": 0,
        "perk2": 8473,
        "perk2Var1": 507,
        "perk2Var2": 0,
        "perk2Var3": 0,
        "perk3": 8453,
        "perk3Var1": 993,
        "perk3Var2": 81,
        "perk3Var3": 0,
        "perk4": 8009,
        "perk4Var1": 854,
        "perk4Var2": 82,
        "perk4Var3": 0,
        "perk5": 9105,
        "perk5Var1": 18,
        "perk5Var2": 20,
        "perk5Var3": 0,
        "perkPrimaryStyle": 8400,
        "perkSubStyle": 8000,
        "statPerk0": 5008,
        "statPerk1": 5008,
        "statPerk2": 5002
      },
      "timeline": {
        "participantId": 10,
        "creepsPerMinDeltas": {
          "10-20": 0.8999999999999999,
          "0-10": 0.1,
          "20-30": 1.4
        },
        "xpPerMinDeltas": {
          "10-20": 432.5,
          "0-10": 231.3,
          "20-30": 320.7
        },
        "goldPerMinDeltas": {
          "10-20": 340.79999999999995,
          "0-10": 206.5,
          "20-30": 236.89999999999998
        },
        "damageTakenPerMinDeltas": {
          "10-20": 904.3,
          "0-10": 581.9,
          "20-30": 986.9
        },
        "role": "NONE",
        "lane": "JUNGLE"
      }
    }
  ],
  "participantIdentities": [
    {
      "participantId": 1,
      "name":"Jaenaryia"
    },
    {
      "participantId": 2,
      "name":"Iniki"
    },
    {
      "participantId": 3,
      "name":"MasterAndo"
    },
    {
      "participantId": 4,
      "name":"Raphib737"
    },
    {
      "participantId": 5,
      "name":"Shooeye"
    },
    {
      "participantId": 6,
      "name":"CindyIsChillen"
    },
    {
      "participantId": 7,
      "name":"Aksynial"
    },
    {
      "participantId": 8,
      "name":"Reved"
    },
    {
      "participantId": 9,
      "name":"Mooogen"
    },
    {
      "participantId": 10,
      "name":"Torpuddo"
    }
  ]
}